{
  "1": {
    "title": "Godot Engine 3.0 is out (with C# support)",
    "link": "https://godotengine.org/article/godot-3-0-released",
    "imageUrl": "https://godotengine.org/storage/app/uploads/public/5a6/f92/d3f/5a6f92d3f0d1d382442473.jpg",
    "createdAt": 1517326755601,
    "user": "Eyal Mor",
    "upVotes": 0,
    "comments": [1]
  },
  "2": {
    "title": "What Really Happened with Vista: An Insider’s Retrospective",
    "link": "https://blog.usejournal.com/what-really-happened-with-vista-an-insiders-retrospective-f713ee77c239",
    "imageUrl": "https://cdn-images-1.medium.com/max/1600/1*7tQ4kI9hVJxGDzo1Ejy42Q.jpeg",
    "createdAt": 1517326755601,
    "user": "Eyal Mor",
    "upVotes": 0,
    "comments": []
  },
  "3": {
    "title": "Choose Your Adventure guide on undoing your git screw-up.",
    "link": "https://sethrobertson.github.io/GitFixUm/fixup.html",
    "imageUrl": "http://s2.quickmeme.com/img/7e/7ec3f9aad4d1fa85ccbbc7e417a481b35defcb2fd9889b4b076d7bcf48591d50.jpg",
    "createdAt": 1517326755601,
    "user": "Eyal Mor",
    "upVotes": 0,
    "comments": []
  },
  "4": {
    "title": "Rust 2018 Roadmap",
    "link": "https://github.com/aturon/rfcs/blob/roadmap-2018/text/0000-roadmap-2018.md",
    "imageUrl": "https://i.imgur.com/xPZRD4c.png",
    "createdAt": 1517326755601,
    "user": "Eyal Mor",
    "upVotes": 0,
    "comments": []
  },
  "5": {
    "title": "Software Complexity Is Killing Us",
    "link": "https://www.simplethread.com/software-complexity-killing-us/",
    "imageUrl": "https://exceptionnotfound.net/content/images/2017/09/two-states-of-programmers.png",
    "createdAt": 1517326755601,
    "user": "Eyal Mor",
    "upVotes": 0,
    "comments": []
  }
}